wworks/__init__.py
wworks/pools.py
wworks/swworks.py
wworks-0.1.0.dist-info/LICENSE
wworks-0.1.0.dist-info/METADATA
wworks-0.1.0.dist-info/WHEEL
wworks-0.1.0.dist-info/top_level.txt
wworks-0.1.0.dist-info/RECORD
