Metadata-Version: 2.1
Name: wworks
Version: 0.1.0
Summary: a light multiprocessing/multithreading work dispatcher for python.
Home-page: https://github.com/LMKA/wworks
Author: Mehdi LAKBIR
Author-email: mehdi.lakbir@gmail.com
License: UNKNOWN
Keywords: python,light,multiprocessing,multithreading,ProcessPoolExecutor,ThreadPoolExecutor
Platform: UNKNOWN
Classifier: Topic :: Software Development :: Libraries :: Python Modules
Classifier: Programming Language :: Python :: 3
Classifier: Programming Language :: Python :: 3.7
Classifier: Programming Language :: Python :: 3.8
Classifier: Programming Language :: Python :: 3.9
Classifier: Intended Audience :: Developers
Classifier: Development Status :: 3 - Alpha
Classifier: License :: OSI Approved :: MIT License
Requires-Python: >=3.7
Requires-Dist: tqdm
